{
    "ls_id": "LS-NN-ST-O-LRLS-LRL",
    "ls_ttl": "Laurel",
    "ls_url": "/ls/nn/st/o/lrls/lrl.json",
    "scion_id": "ls_nn_st_o_lrls_lrl",
    "scions": [
        {
            "drct_id": "SYMB",
            "drct_ttl": "Symbols + Symbolism of 'Laurel'",
            "scion_id": "ls_nn_st_o_lrls_lrl_symb",
            "scions": [
                {
                    "insc_typ1": "stm",
                    "insc_typ2": "brnch",
                    "insc_tag": "Symbolizes",
                    "insc_ttl": "<span class='styl_stm_ttl_spprt'>Things</span>&nbsp;<span class='styl_stm_ttl_tny'>that</span>&nbsp;<span class='styl_stm_ttl_opncls'>(</span><span class='styl_stm_ttl_trm'>Laurel</span><span class='styl_stm_ttl_opncls'>)</span>&nbsp;<span class='styl_stm_ttl_tny'>symbolizes</span>",
                    "scion_id": "ls_nn_st_o_lrls_lrl_symb_lst_symblzes",
                    "scions": [
                        {
                            "insc_typ1": "insc",
                            "insc_typ2": "trm",
                            "insc_tag": "Symbolizes",
                            "insc_term": "Success // Victory",
                            "scion_id": "ls_nn_st_o_lrls_lrl_symb_lst_symblzes_i_successvictory",
                            "scions": [
                                {
                                    "insc_typ1": "insc",
                                    "insc_typ2": "txt_stpl",
                                    "insc_tag": "Usage",
                                    "insc_sld": "\\_",
                                    "insc_cntn": "<span class='styl_insc_txt_trm_grg'>The Laurel Garland</span>&nbsp;(<span class='styl_insc_txt_itc'>which remains evergreen/immortal</span>)\n\tis&nbsp;<span class='styl_insc_txt_trm_stkbld'>a symbol of success</span>&nbsp;in the arts."
                                },
                                {
                                    "insc_typ1": "insc",
                                    "insc_typ2": "txt_stpl",
                                    "insc_tag": "Usage",
                                    "insc_sld": "\\_",
                                    "insc_offs": "styl_offs_dwn_17",
                                    "insc_cntn": "The&nbsp;<span class='styl_insc_txt_trm_grg'>leaves of the Laurel Tree</span>&nbsp;were used by the ancient Greeks\nand Romans&nbsp;<span class='styl_insc_txt_trm_stkbld'>to crown their victors</span>&nbsp;(<span class='styl_insc_txt_itc'>such as at the Pythian Games</span>)."
                                }
                            ]
                        }
                    ]
                }
            ]
        }
    ]
}
